{
  "cookies": [
    {
      "name": "dtCookie",
      "value": "v_4_srv_40_sn_14D48939004CD238080B01777E9C8205_perc_100000_ol_0_mul_1_app-3A47d4c64c3b67ec69_1_rcs-3Acss_0",
      "domain": ".europa.eu",
      "path": "/",
      "expires": -1,
      "httpOnly": false,
      "secure": false,
      "sameSite": "Lax"
    },
    {
      "name": "ELX_SESSIONID",
      "value": "1DUm_og2Ak9MoDtol37e6VUHRvVNNw0krc3R9dYBTM4FXtNHWFLc!-163575895",
      "domain": "eur-lex.europa.eu",
      "path": "/",
      "expires": -1,
      "httpOnly": true,
      "secure": true,
      "sameSite": "Lax"
    },
    {
      "name": "experimentalFeaturesActivated",
      "value": "false",
      "domain": "eur-lex.europa.eu",
      "path": "/",
      "expires": 1764179204.898433,
      "httpOnly": false,
      "secure": false,
      "sameSite": "Lax"
    },
    {
      "name": "rxVisitor",
      "value": "1761587205038RA8PTGN4J3UGD26S88KITE3R99OP37AN",
      "domain": ".europa.eu",
      "path": "/",
      "expires": -1,
      "httpOnly": false,
      "secure": false,
      "sameSite": "Lax"
    },
    {
      "name": "dtSa",
      "value": "-",
      "domain": ".europa.eu",
      "path": "/",
      "expires": -1,
      "httpOnly": false,
      "secure": false,
      "sameSite": "Lax"
    },
    {
      "name": "rxvt",
      "value": "1761589005088|1761587205040",
      "domain": ".europa.eu",
      "path": "/",
      "expires": -1,
      "httpOnly": false,
      "secure": false,
      "sameSite": "Lax"
    },
    {
      "name": "dtPC",
      "value": "40$587205036_532h-vUHJOWUWFMKLFHUPCUKPHUAJTWJMQVRAS-0e0",
      "domain": ".europa.eu",
      "path": "/",
      "expires": -1,
      "httpOnly": false,
      "secure": false,
      "sameSite": "Lax"
    },
    {
      "name": "AWSALB",
      "value": "EVJlWobWaWZtzIDwLXuo5TgSFz8fA0MYrOB8/gT87gvKEHzT9Ph2ON3jmPdIw2sCX75HF9izUKlq85kOs+0UyGmnpm2LL7/VXQ2EYQNQ+JYKSlfLIwm/P85MrcH0",
      "domain": "eur-lex.europa.eu",
      "path": "/",
      "expires": 1762192006.32019,
      "httpOnly": false,
      "secure": false,
      "sameSite": "Lax"
    }
  ],
  "origins": []
}